crop_people_cli/__init__.py
crop_people_cli/crop_people_cli.py
crop_people_cli/commands/__init__.py
crop_people_cli/commands/multi.py
crop_people_cli/commands/single.py
crop_people_cli-1.4.2.dist-info/METADATA
crop_people_cli-1.4.2.dist-info/WHEEL
crop_people_cli-1.4.2.dist-info/entry_points.txt
crop_people_cli-1.4.2.dist-info/RECORD
