Metadata-Version: 2.3
Name: crop-people-cli
Version: 1.4.2
Summary: CLI tool to crop people from images using YOLOvX
Author-email: tadeasf <business@tadeasfort.com>
Requires-Python: >=3.12
Requires-Dist: loguru>=0.7.2
Requires-Dist: opencv-python>=4.10.0.84
Requires-Dist: prompt-toolkit>=3.0.48
Requires-Dist: typer>=0.12.5
Requires-Dist: ultralytics>=8.3.14
